ai_git_cli/__init__.py
ai_git_cli/ai_client.py
ai_git_cli/commit_execution.py
ai_git_cli/commit_message.py
ai_git_cli/config.py
ai_git_cli/diff_analysis.py
ai_git_cli/grouping.py
ai_git_cli/main.py
ai_git_cli/prompts.py
ai_git_cli/utils.py
tests/__init__.py
tests/test_cli.py
ai_git_cli-0.1.6.dist-info/LICENSE
ai_git_cli-0.1.6.dist-info/METADATA
ai_git_cli-0.1.6.dist-info/WHEEL
ai_git_cli-0.1.6.dist-info/entry_points.txt
ai_git_cli-0.1.6.dist-info/top_level.txt
ai_git_cli-0.1.6.dist-info/RECORD
