Metadata-Version: 2.1
Name: ai-git-cli
Version: 0.1.6
Summary: An AI-powered Git commit message generator and manager.
Home-page: https://github.com/TerminalGravity/ai-git-cli
Author: terminalgravity
Author-email: jrinnfelke@gmail.com
Classifier: Programming Language :: Python :: 3
Classifier: Operating System :: OS Independent
Requires-Python: >=3.7
License-File: LICENSE
Requires-Dist: GitPython>=3.1.0
Requires-Dist: openai>=1.0.0
Requires-Dist: rich>=12.0.0
Requires-Dist: PyYAML>=6.0
Requires-Dist: pydantic>=1.10.0
Requires-Dist: python-dotenv>=0.19.0
